odoo/addons/purchase_line_reassign/README.rst
odoo/addons/purchase_line_reassign/__init__.py
odoo/addons/purchase_line_reassign/__manifest__.py
odoo/addons/purchase_line_reassign/i18n/es.po
odoo/addons/purchase_line_reassign/i18n/it.po
odoo/addons/purchase_line_reassign/i18n/purchase_line_reassign.pot
odoo/addons/purchase_line_reassign/readme/CONFIGURE.md
odoo/addons/purchase_line_reassign/readme/CONTRIBUTORS.md
odoo/addons/purchase_line_reassign/readme/DESCRIPTION.md
odoo/addons/purchase_line_reassign/readme/USAGE.md
odoo/addons/purchase_line_reassign/security/ir.model.access.csv
odoo/addons/purchase_line_reassign/static/description/icon.png
odoo/addons/purchase_line_reassign/static/description/index.html
odoo/addons/purchase_line_reassign/tests/__init__.py
odoo/addons/purchase_line_reassign/tests/test_reassign.py
odoo/addons/purchase_line_reassign/wizards/__init__.py
odoo/addons/purchase_line_reassign/wizards/purchase_line_reassign_view.xml
odoo/addons/purchase_line_reassign/wizards/purchase_line_reassign_wiz.py
odoo_addon_purchase_line_reassign-18.0.1.0.0.3.dist-info/METADATA
odoo_addon_purchase_line_reassign-18.0.1.0.0.3.dist-info/WHEEL
odoo_addon_purchase_line_reassign-18.0.1.0.0.3.dist-info/top_level.txt
odoo_addon_purchase_line_reassign-18.0.1.0.0.3.dist-info/RECORD
